MANIFEST.in
README.md
requirements.pip
setup.py
il2ds_middleware/__init__.py
il2ds_middleware/constants.py
il2ds_middleware/parser.py
il2ds_middleware/protocol.py
il2ds_middleware/regex.py
il2ds_middleware/requests.py
il2ds_middleware/service.py
il2ds_middleware/utils.py
il2ds_middleware.egg-info/PKG-INFO
il2ds_middleware.egg-info/SOURCES.txt
il2ds_middleware.egg-info/dependency_links.txt
il2ds_middleware.egg-info/requires.txt
il2ds_middleware.egg-info/top_level.txt
il2ds_middleware/ds_emulator/__init__.py
il2ds_middleware/ds_emulator/constants.py
il2ds_middleware/ds_emulator/protocol.py
il2ds_middleware/ds_emulator/service.py
il2ds_middleware/ds_emulator/tests/__init__.py
il2ds_middleware/ds_emulator/tests/test_console.py
il2ds_middleware/ds_emulator/tests/test_device_link.py
il2ds_middleware/ds_emulator/tests/test_events_log.py
il2ds_middleware/ds_emulator/tests/test_service.py
il2ds_middleware/interface/__init__.py
il2ds_middleware/interface/parser.py
il2ds_middleware/interface/service.py
il2ds_middleware/tests/__init__.py
il2ds_middleware/tests/service.py
il2ds_middleware/tests/test_parser.py
il2ds_middleware/tests/test_protocol.py
il2ds_middleware/tests/test_service.py