Metadata-Version: 1.1
Name: il2ds-middleware
Version: 0.10.3
Summary: High-level access to IL-2 FB Dedicated Server.
Home-page: https://github.com/IL2HorusTeam/il2ds-middleware
Author: Alexander Oblovatniy
Author-email: oblovatniy@gmail.com
License: GPLv2
Platform: UNKNOWN
Classifier: Development Status :: 4 - Beta
Classifier: Intended Audience :: Developers
Classifier: License :: Free for non-commercial use
Classifier: License :: OSI Approved :: GNU General Public License v2 (GPLv2)
Classifier: Natural Language :: English
Classifier: Operating System :: OS Independent
Classifier: Programming Language :: Python :: 2.7
Classifier: Topic :: Software Development :: Libraries
